{
"type": "FeatureCollection",
"name": "budaya",
"crs": { "type": "name", "properties": { "name": "urn:ogc:def:crs:OGC:1.3:CRS84" } },
"features": [
{ "type": "Feature", "properties": { "id": 1, "Nama": "Annisa", "Kegiatan": "Hadroh" }, "geometry": { "type": "Point", "coordinates": [ 110.393411788018156, -7.806727592690189 ] } },
{ "type": "Feature", "properties": { "id": 2, "Nama": "Ummahatul Mursyidin", "Kegiatan": "Hadroh" }, "geometry": { "type": "Point", "coordinates": [ 110.397415618766686, -7.79980994205531 ] } },
{ "type": "Feature", "properties": { "id": 3, "Nama": "Laras Budaya", "Kegiatan": "Panembromo" }, "geometry": { "type": "Point", "coordinates": [ 110.395262798739466, -7.797715411379044 ] } },
{ "type": "Feature", "properties": { "id": 4, "Nama": "Turonggo Mudho Sekar Rinonce", "Kegiatan": "Jathilan" }, "geometry": { "type": "Point", "coordinates": [ 110.397527016192839, -7.798756847782092 ] } },
{ "type": "Feature", "properties": { "id": 5, "Nama": "Wira Praja Manggala", "Kegiatan": "Bergodo" }, "geometry": { "type": "Point", "coordinates": [ 110.390328564704134, -7.799489664335208 ] } },
{ "type": "Feature", "properties": { "id": 6, "Nama": "Chandra Maya", "Kegiatan": "Tari" }, "geometry": { "type": "Point", "coordinates": [ 110.392486930316963, -7.803226993337925 ] } },
{ "type": "Feature", "properties": { "id": 8, "Nama": "Chandra Kinasih", "Kegiatan": "Tari" }, "geometry": { "type": "Point", "coordinates": [ 110.3902793425856, -7.79947152987048 ] } }
]
}
